.gitignore
.gitmodules
LICENSE
README.md
edmunds-instance
mkdocs.yml
requirements.txt
setup.cfg
setup.config.ini
setup.py
.circleci/config.yml
.circleci/gh-pages.config.yml
config/app.py
docs/index.md
docs/coreconcepts/applicationmiddleware.md
docs/coreconcepts/serviceproviders.md
docs/data/caching.md
docs/data/database.md
docs/data/migrations.md
docs/data/orm.md
docs/data/storage.md
docs/gettingstarted/configuration.md
docs/gettingstarted/console.md
docs/gettingstarted/debuggingandprofiling.md
docs/gettingstarted/errorsandlogging.md
docs/gettingstarted/installation.md
docs/http/inputandvalidation.md
docs/http/request.md
docs/http/requestmiddleware.md
docs/http/response.md
docs/http/routing.md
docs/http/session.md
docs/http/visitor.md
docs/localization/formatting.md
docs/localization/localization.md
docs/localization/location.md
docs/localization/translations.md
docs/testing/gettingstarted.md
edmunds/__init__.py
edmunds/application.py
edmunds/globals.py
edmunds-instance/__init__.py
edmunds-instance/appengine_config.py
edmunds-instance/main.py
edmunds-instance/manage.py
edmunds-instance/app/__init__.py
edmunds-instance/app/console/__init__.py
edmunds-instance/app/console/manager.py
edmunds-instance/app/console/commands/__init__.py
edmunds-instance/app/console/commands/helloworldcommand.py
edmunds-instance/app/database/__init__.py
edmunds-instance/app/database/models/__init__.py
edmunds-instance/app/database/models/role.py
edmunds-instance/app/database/models/user.py
edmunds-instance/app/database/tables/__init__.py
edmunds-instance/app/database/tables/userstable.py
edmunds-instance/app/exceptions/__init__.py
edmunds-instance/app/exceptions/handler.py
edmunds-instance/app/foundation/__init__.py
edmunds-instance/app/foundation/myapplicationmiddleware.py
edmunds-instance/app/http/__init__.py
edmunds-instance/app/http/routes.py
edmunds-instance/app/http/controllers/__init__.py
edmunds-instance/app/http/controllers/homecontroller.py
edmunds_fw.egg-info/PKG-INFO
edmunds_fw.egg-info/SOURCES.txt
edmunds_fw.egg-info/dependency_links.txt
edmunds_fw.egg-info/requires.txt
edmunds_fw.egg-info/top_level.txt
