Metadata-Version: 1.1
Name: edmunds-fw
Version: 0.2.15
Summary: Edmunds is a fast Python framework for building web applications with a firm base to start from.
Home-page: https://github.com/LowieHuyghe/edmunds
Author: Lowie Huyghe
Author-email: iam@lowiehuyghe.com
License: Apache-2.0
Platform: UNKNOWN
Classifier: Development Status :: 3 - Alpha
Classifier: Programming Language :: Python :: 3.6
Classifier: Programming Language :: Python :: 3.5
Classifier: Programming Language :: Python :: 3.4
Classifier: License :: OSI Approved :: Apache Software License
Classifier: Topic :: Software Development :: Libraries :: Application Frameworks
Classifier: Intended Audience :: Developers
Classifier: Programming Language :: Python :: 2
Classifier: Programming Language :: Python :: 3
Classifier: Programming Language :: Python :: 2.7
